git_auto_pro/__init__.py
git_auto_pro/backup.py
git_auto_pro/cli.py
git_auto_pro/config.py
git_auto_pro/git_commands.py
git_auto_pro/github.py
git_auto_pro/github_issues.py
git_auto_pro/gitignore_manager.py
git_auto_pro/scaffolding/__init__.py
git_auto_pro/scaffolding/github_templates.py
git_auto_pro/scaffolding/gitignore.py
git_auto_pro/scaffolding/hooks.py
git_auto_pro/scaffolding/license.py
git_auto_pro/scaffolding/project.py
git_auto_pro/scaffolding/readme.py
git_auto_pro/scaffolding/templates.py
git_auto_pro/scaffolding/workflows.py
git_auto_pro-1.1.1.dist-info/licenses/LICENSE
git_auto_pro-1.1.1.dist-info/METADATA
git_auto_pro-1.1.1.dist-info/WHEEL
git_auto_pro-1.1.1.dist-info/entry_points.txt
git_auto_pro-1.1.1.dist-info/top_level.txt
git_auto_pro-1.1.1.dist-info/RECORD
