Metadata-Version: 2.4
Name: git-auto-pro
Version: 1.1.1
Summary: Complete Git + GitHub automation CLI tool with interactive file management
Home-page: https://github.com/HimanshuSingh-966/git-auto-pro
Author: Himanshu Singh
Author-email: Himanshu Singh <choudharyhimanshusingh966@gmail.com>
Maintainer-email: Himanshu Singh <choudharyhimanshusingh966@gmail.com>
License: MIT
Project-URL: Homepage, https://github.com/HimanshuSingh-966/git-auto-pro
Project-URL: Documentation, https://github.com/HimanshuSingh-966/git-auto-pro/blob/main/README.md
Project-URL: Repository, https://github.com/HimanshuSingh-966/git-auto-pro
Project-URL: Issues, https://github.com/HimanshuSingh-966/git-auto-pro/issues
Keywords: git,github,cli,automation,devtools,gitignore,interactive
Classifier: Development Status :: 4 - Beta
Classifier: Intended Audience :: Developers
Classifier: License :: OSI Approved :: MIT License
Classifier: Programming Language :: Python :: 3
Classifier: Programming Language :: Python :: 3.8
Classifier: Programming Language :: Python :: 3.9
Classifier: Programming Language :: Python :: 3.10
Classifier: Programming Language :: Python :: 3.11
Classifier: Programming Language :: Python :: 3.12
Requires-Python: >=3.8
License-File: LICENSE
Requires-Dist: typer[all]>=0.9.0
Requires-Dist: requests>=2.31.0
Requires-Dist: keyring>=24.0.0
Requires-Dist: rich>=13.0.0
Requires-Dist: gitpython>=3.1.40
Requires-Dist: pyyaml>=6.0
Requires-Dist: questionary>=2.0.0
Provides-Extra: dev
Requires-Dist: pytest>=7.4.0; extra == "dev"
Requires-Dist: pytest-cov>=4.1.0; extra == "dev"
Requires-Dist: black>=23.0.0; extra == "dev"
Requires-Dist: ruff>=0.1.0; extra == "dev"
Requires-Dist: mypy>=1.5.0; extra == "dev"
Dynamic: author
Dynamic: home-page
Dynamic: license-file
Dynamic: requires-python
